pose_per_frame
