Metadata-Version: 1.1
Name: pose-per-frame
Version: 0.2
Summary: get pose prediction, given a frame and a model
Home-page: UNKNOWN
Author: Rafael RazorLabs
Author-email: rafael@razor-labs.com
License: UNKNOWN
Platform: UNKNOWN
Classifier: Programming Language :: Python :: 3.6
